docs/tutorial/conclusion.txt
docs/tutorial/encoding.txt
docs/tutorial/file-format.txt
docs/tutorial/index.txt
docs/tutorial/introduction.txt
docs/tutorial/object-store.txt
docs/tutorial/porcelain.txt
docs/tutorial/remote.txt
docs/tutorial/repo.txt
docs/tutorial/tag.txt
dulwich/__init__.py
dulwich/archive.py
dulwich/client.py
dulwich/config.py
dulwich/diff_tree.py
dulwich/errors.py
dulwich/fastexport.py
dulwich/file.py
dulwich/greenthreads.py
dulwich/hooks.py
dulwich/ignore.py
dulwich/index.py
dulwich/line_ending.py
dulwich/log_utils.py
dulwich/lru_cache.py
dulwich/mailmap.py
dulwich/object_store.py
dulwich/objects.py
dulwich/objectspec.py
dulwich/pack.py
dulwich/patch.py
dulwich/porcelain.py
dulwich/protocol.py
dulwich/reflog.py
dulwich/refs.py
dulwich/repo.py
dulwich/server.py
dulwich/stash.py
dulwich/stdint.h
dulwich/walk.py
dulwich/web.py
dulwich/contrib/__init__.py
dulwich/contrib/paramiko_vendor.py
dulwich/contrib/release_robot.py
dulwich/contrib/swift.py
dulwich/contrib/test_release_robot.py
dulwich/contrib/test_swift.py
dulwich/contrib/test_swift_smoke.py
dulwich/tests/__init__.py
dulwich/tests/test_archive.py
dulwich/tests/test_blackbox.py
dulwich/tests/test_client.py
dulwich/tests/test_config.py
dulwich/tests/test_diff_tree.py
dulwich/tests/test_fastexport.py
dulwich/tests/test_file.py
dulwich/tests/test_grafts.py
dulwich/tests/test_greenthreads.py
dulwich/tests/test_hooks.py
dulwich/tests/test_ignore.py
dulwich/tests/test_index.py
dulwich/tests/test_line_ending.py
dulwich/tests/test_lru_cache.py
dulwich/tests/test_mailmap.py
dulwich/tests/test_missing_obj_finder.py
dulwich/tests/test_object_store.py
dulwich/tests/test_objects.py
dulwich/tests/test_objectspec.py
dulwich/tests/test_pack.py
dulwich/tests/test_patch.py
dulwich/tests/test_porcelain.py
dulwich/tests/test_protocol.py
dulwich/tests/test_reflog.py
dulwich/tests/test_refs.py
dulwich/tests/test_repository.py
dulwich/tests/test_server.py
dulwich/tests/test_stash.py
dulwich/tests/test_utils.py
comet_git_pure-0.19.15.dist-info/AUTHORS
comet_git_pure-0.19.15.dist-info/COPYING
comet_git_pure-0.19.15.dist-info/METADATA
comet_git_pure-0.19.15.dist-info/WHEEL
comet_git_pure-0.19.15.dist-info/top_level.txt
comet_git_pure-0.19.15.dist-info/RECORD
